MANIFEST.in
README.rst
setup.py
py_oauth2.egg-info/PKG-INFO
py_oauth2.egg-info/SOURCES.txt
py_oauth2.egg-info/dependency_links.txt
py_oauth2.egg-info/requires.txt
py_oauth2.egg-info/top_level.txt
pyoauth2/__init__.py
pyoauth2/client.py
pyoauth2/libs/__init__.py
pyoauth2/libs/access_token.py
pyoauth2/libs/auth_code.py
pyoauth2/libs/base.py
pyoauth2/libs/connection.py
pyoauth2/libs/password.py
pyoauth2/libs/request.py
pyoauth2/libs/response.py
pyoauth2/libs/utils.py