Metadata-Version: 1.1
Name: py-oauth2
Version: 0.0.8
Summary: A Python wrapper for the OAuth 2.0 specification.
Home-page: https://github.com/liluo/py-oauth2
Author: liluo
Author-email: i@liluo.org
License: MIT License
Keywords: Python,pyoauth2,OAuth2,Douban,GitHub,Weibo
Platform: any
Classifier: Environment :: Web Environment
Classifier: Intended Audience :: Developers
Classifier: License :: OSI Approved :: MIT License
Classifier: Operating System :: OS Independent
Classifier: Programming Language :: Python
Classifier: Programming Language :: Python :: 2.7
Classifier: Programming Language :: Python :: 3.2
Classifier: Programming Language :: Python :: 3.3
Classifier: Topic :: Internet :: WWW/HTTP :: Dynamic Content
Classifier: Topic :: Software Development :: Libraries :: Python Modules
